d2irclient/D2IRClient.py
d2irclient/__init__.py
d2irclient/_httpx.py
d2irclient-0.1.1.dist-info/WHEEL
d2irclient-0.1.1.dist-info/METADATA
d2irclient-0.1.1.dist-info/RECORD
