Metadata-Version: 2.3
Name: d2irclient
Version: 0.1.1
Summary: A python client for the Direct to INN-Reach (D2IR) API
Requires-Dist: httpx>=0.28.1
Requires-Python: >=3.11, <4.0
